{
    "title": "Креативное пространство «Люмьер-Холл»",
    "imgs": [
        "https://kudago.com/media/images/place/72/fd/72fdca056b037c8f7eff5ac304d73282.jpg",
        "https://kudago.com/media/images/place/5f/97/5f97c76c6c6b05616050ede5cb477184.jpg",
        "https://kudago.com/media/images/place/2b/51/2b511e0518a9663d692130306fa7d29a.jpg",
        "https://kudago.com/media/images/place/19/92/199286f87b6eed5872d03de91b2e3744.jpg",
        "https://kudago.com/media/images/place/b7/62/b7625475fce8967a2fbef865f66708e9.jpg",
        "https://kudago.com/media/images/place/ba/f3/baf3c540403fb0057cf839849f8d92f6.jpg"
    ],
    "description_short": "В креативном пространстве «Люмьер-Холл», благодаря мультимедийным выставкам оживают полотна великих мастеров, ценители кинематографа получают удовольствие от тематических кинопоказов, а на концертах и фестивалях кипит яркая, современная, полная впечатлений жизнь.",
    "description_long": "<p>В большом мультимедийном зале «Люмьер-Холла» установлено двадцать панорамных экранов с разрешением 6 тысяч пикселей. Объёмный звук, общая площадь изображения 500 квадратных метров, 2D- и 3D-анимация, технология мультипоточного проецирования создают у гостей эффект полного присутствия. Здесь, в мультимедийном зале, проходят выставки, кинопоказы, музыкальные концерты, фестивали, презентации и деловые встречи.</p><p>На выставках формата «ожившие полотна» зрители могут полюбоваться картинами известных художников сразу на множестве экранов. Изображение проецируется в формате Full HD и сопровождается объёмным звуковым рядом. Картины приближаются и отдаляются, детали и предметы приходят в движение, и посетители словно погружаются в творческие миры живописцев.</p><p>В «Люмьер-Холле» регулярно проходят тематические кинопоказы. Организаторы радуют эстетов подборками чёрно-белых лент, демонстрируют анимационные фильмы, устраивают ретроспективы звёздных режиссёров и балуют публику новыми хитами. Зрители располагаются на мягких пуфиках, причём сами выбирают, где их разместить. Для тех, кто предпочитает классические показы, работает зал с одним экраном.</p><p>Перекусить и выпить чашечку кофе можно в кафе «Люмьер-Холла».</p><p>Подробности узнавайте <a class=\"external-link\" href=\"http://www.lumierehall.ru/msk\" rel=\"nofollow\" target=\"_blank\">на сайте</a>. За расписанием показов и выставок следите <a class=\"external-link\" href=\"https://vk.com/club87604121\" rel=\"nofollow\" target=\"_blank\">«ВКонтакте»</a>.</p>",
    "coordinates": {
        "lng": "37.58440699999958",
        "lat": "55.80563009999988"
    }
}